odoo/addons/loyalty_partner_applicability/README.rst
odoo/addons/loyalty_partner_applicability/__init__.py
odoo/addons/loyalty_partner_applicability/__manifest__.py
odoo/addons/loyalty_partner_applicability/i18n/it.po
odoo/addons/loyalty_partner_applicability/i18n/loyalty_partner_applicability.pot
odoo/addons/loyalty_partner_applicability/models/__init__.py
odoo/addons/loyalty_partner_applicability/models/loyalty_program.py
odoo/addons/loyalty_partner_applicability/models/res_config_settings.py
odoo/addons/loyalty_partner_applicability/readme/CONTRIBUTORS.md
odoo/addons/loyalty_partner_applicability/readme/DESCRIPTION.md
odoo/addons/loyalty_partner_applicability/readme/USAGE.md
odoo/addons/loyalty_partner_applicability/static/description/icon.png
odoo/addons/loyalty_partner_applicability/static/description/index.html
odoo/addons/loyalty_partner_applicability/tests/__init__.py
odoo/addons/loyalty_partner_applicability/tests/common.py
odoo/addons/loyalty_partner_applicability/tests/test_loyalty_partner_applicability.py
odoo/addons/loyalty_partner_applicability/views/loyalty_program_view_form.xml
odoo_addon_loyalty_partner_applicability-18.0.1.0.0.2.dist-info/METADATA
odoo_addon_loyalty_partner_applicability-18.0.1.0.0.2.dist-info/WHEEL
odoo_addon_loyalty_partner_applicability-18.0.1.0.0.2.dist-info/top_level.txt
odoo_addon_loyalty_partner_applicability-18.0.1.0.0.2.dist-info/RECORD
