Metadata-Version: 2.1
Name: odoo-addon-loyalty_partner_applicability
Version: 18.0.1.0.0.2
Requires-Python: >=3.10
Requires-Dist: odoo==18.0.*
Summary: Enables the definition of a customer filter for promotion rules that will only be applied to customers who meet the specified conditions in the filter.
Home-page: https://github.com/OCA/sale-promotion
License: AGPL-3
Author: Tecnativa,ACSONE SA/NV,Odoo Community Association (OCA)
Author-email: support@odoo-community.org
Classifier: Programming Language :: Python
Classifier: Framework :: Odoo
Classifier: Framework :: Odoo :: 18.0
Classifier: License :: OSI Approved :: GNU Affero General Public License v3
